otlp_test_data/__init__.py
otlp_test_data/py.typed
otlp_test_data-1.0.1.dist-info/METADATA
otlp_test_data-1.0.1.dist-info/WHEEL
otlp_test_data-1.0.1.dist-info/RECORD
