Metadata-Version: 2.4
Name: otlp-test-data
Version: 1.0.1
Summary: Produces OTLP data using OTEL instrumentation
Project-URL: Repository, https://github.com/dimaqq/otlp-test-data
Project-URL: Issues, https://github.com/dimaqq/otlp-test-data/issues
License: Apache License (2.0)
Classifier: Development Status :: 3 - Alpha
Classifier: Framework :: OpenTelemetry
Classifier: Framework :: OpenTelemetry :: Exporters
Classifier: Intended Audience :: Developers
Classifier: License :: OSI Approved :: Apache Software License
Classifier: Natural Language :: English
Classifier: Operating System :: OS Independent
Classifier: Programming Language :: Python
Classifier: Programming Language :: Python :: 3
Classifier: Programming Language :: Python :: 3 :: Only
Classifier: Programming Language :: Python :: 3.8
Classifier: Programming Language :: Python :: 3.9
Classifier: Programming Language :: Python :: 3.10
Classifier: Programming Language :: Python :: 3.11
Classifier: Programming Language :: Python :: 3.12
Classifier: Programming Language :: Python :: 3.13
Classifier: Programming Language :: Python :: 3.14
Classifier: Programming Language :: Python :: Implementation :: CPython
Classifier: Programming Language :: Python :: Implementation :: PyPy
Classifier: Topic :: Software Development :: Testing
Classifier: Topic :: Software Development :: Testing :: Traffic Generation
Requires-Python: >=3.8
Requires-Dist: freezegun~=1.5
Requires-Dist: grpcio<2.0.0,>=1.66.2; python_version >= '3.13'
Requires-Dist: opentelemetry-api~=1.30
Requires-Dist: opentelemetry-exporter-otlp-proto-http~=1.30
Requires-Dist: opentelemetry-exporter-otlp~=1.30
